armctl/__init__.py
armctl/_blank/robot.py
armctl/dobot/README.md
armctl/dobot/__init__.py
armctl/dobot/dobot.py
armctl/elephant_robotics/README.md
armctl/elephant_robotics/__init__.py
armctl/elephant_robotics/elephant_robotics.py
armctl/elephant_robotics/mycobot.py
armctl/fanuc/__init__.py
armctl/fanuc/fanuc.py
armctl/jaka/README.md
armctl/jaka/__init__.py
armctl/jaka/jaka.py
armctl/templates/__init__.py
armctl/templates/commands.py
armctl/templates/communication.py
armctl/templates/logger.py
armctl/templates/plc_controller.py
armctl/templates/properties.py
armctl/templates/serial_controller.py
armctl/templates/socket_controller.py
armctl/universal_robots/README.md
armctl/universal_robots/__init__.py
armctl/universal_robots/manipulators/__init__.py
armctl/universal_robots/manipulators/on_robot.py
armctl/universal_robots/protocols/config.xml
armctl/universal_robots/protocols/rtde.py
armctl/universal_robots/universal_robots.py
armctl/universal_robots/urx.py
armctl/utils/__init__.py
armctl/utils/command_check.py
armctl/utils/network_scanner.py
armctl/utils/units.py
armctl/vention/README.md
armctl/vention/__init__.py
armctl/vention/vention.py
armctl-0.3.4.dist-info/WHEEL
armctl-0.3.4.dist-info/METADATA
armctl-0.3.4.dist-info/RECORD
