Metadata-Version: 2.3
Name: armctl
Version: 0.3.4
Summary: Agnostic Robotic Manipulator Controller (armctl)
Keywords: robotics,socket,control,automation,ur,universal robotics,jaka,dobot,elephant robotics,vention,fanuc
Author: Michael Gross
Author-email: Michael Gross <MGross21@users.noreply.github.com>
License: MIT License
Classifier: Programming Language :: Python :: 3
Classifier: License :: OSI Approved :: MIT License
Classifier: Operating System :: OS Independent
Classifier: Development Status :: 4 - Beta
Requires-Dist: urrtde
Requires-Python: >=3.6
Project-URL: Homepage, https://github.com/MGross21/armctl
Project-URL: Issues, https://github.com/MGross21/armctl/issues
